<colors query="david hume">

<color name="black" weight="0.742856368164">
 <shade name="weak" weight="0.399999520001" />
 <shade name="light" weight="0.29999964" />
 <shade name="dark" weight="0.29999964" />
</color>

<color name="red" weight="0.114285595102">
 <shade name="weak" weight="0.399999520001" />
 <shade name="light" weight="0.29999964" />
 <shade name="dark" weight="0.29999964" />
</color>

<color name="white" weight="0.0571427975511">
 <shade name="weak" weight="0.399999520001" />
 <shade name="light" weight="0.29999964" />
 <shade name="dark" weight="0.29999964" />
</color>

<color name="orange" weight="0.0571427975511">
 <shade name="weak" weight="0.399999520001" />
 <shade name="light" weight="0.29999964" />
 <shade name="dark" weight="0.29999964" />
</color>

<color name="purple" weight="0.0285713987755">
 <shade name="weak" weight="0.399999520001" />
 <shade name="light" weight="0.29999964" />
 <shade name="dark" weight="0.29999964" />
</color>

</colors>