<colors query="will durant">

<color name="green" weight="0.583332750001">
 <shade name="light" weight="0.699999230001" />
 <shade name="weak" weight="0.29999967" />
 <shade name="soft" weight="0.0" />
</color>

<color name="red" weight="0.1666665">
 <shade name="light" weight="0.636363000001" />
 <shade name="weak" weight="0.272727" />
 <shade name="warm" weight="0.0909090000001" />
</color>

<color name="black" weight="0.1666665">
 <shade name="light" weight="0.636363000001" />
 <shade name="weak" weight="0.272727" />
 <shade name="warm" weight="0.0909090000001" />
</color>

<color name="white" weight="0.0833332500001">
 <shade name="light" weight="0.636363000001" />
 <shade name="weak" weight="0.272727" />
 <shade name="warm" weight="0.0909090000001" />
</color>

<color name="yellow" weight="0.0">
 <shade name="light" weight="0.636363000001" />
 <shade name="weak" weight="0.272727" />
 <shade name="warm" weight="0.0909090000001" />
</color>

</colors>