<colors query="new york house">

<color name="orange" weight="0.4999995">
 <shade name="dark" weight="0.49999938889" />
 <shade name="hard" weight="0.277777438272" />
 <shade name="light" weight="0.222221950618" />
</color>

<color name="green" weight="0.333333">
 <shade name="dark" weight="0.49999938889" />
 <shade name="hard" weight="0.277777438272" />
 <shade name="light" weight="0.222221950618" />
</color>

<color name="white" weight="0.1666665">
 <shade name="dark" weight="0.49999938889" />
 <shade name="hard" weight="0.277777438272" />
 <shade name="light" weight="0.222221950618" />
</color>

<color name="yellow" weight="0.0">
 <shade name="dark" weight="0.49999938889" />
 <shade name="hard" weight="0.277777438272" />
 <shade name="light" weight="0.222221950618" />
</color>

<color name="red" weight="0.0">
 <shade name="dark" weight="0.49999938889" />
 <shade name="hard" weight="0.277777438272" />
 <shade name="light" weight="0.222221950618" />
</color>

</colors>