<colors query="organum">

<color name="orange" weight="0.333333">
 <shade name="light" weight="0.599999400001" />
 <shade name="hard" weight="0.3999996" />
 <shade name="weak" weight="0.0" />
</color>

<color name="black" weight="0.333333">
 <shade name="light" weight="0.599999400001" />
 <shade name="hard" weight="0.3999996" />
 <shade name="weak" weight="0.0" />
</color>

<color name="yellow" weight="0.1666665">
 <shade name="light" weight="0.599999400001" />
 <shade name="hard" weight="0.3999996" />
 <shade name="weak" weight="0.0" />
</color>

<color name="red" weight="0.1666665">
 <shade name="light" weight="0.599999400001" />
 <shade name="hard" weight="0.3999996" />
 <shade name="weak" weight="0.0" />
</color>

<color name="white" weight="0.0">
 <shade name="light" weight="0.599999400001" />
 <shade name="hard" weight="0.3999996" />
 <shade name="weak" weight="0.0" />
</color>

</colors>